{
  "@context": "https://schema.org",
  "@graph": [
    {
      "@type": "Service",
      "@id": "https://www.nexus-clinic.com/hair/exosome-hair-treatment-malaysia/#service",
      "name": "Exosome Hair Loss Treatment in Malaysia for Advanced Hair Regeneration",
      "url": "https://www.nexus-clinic.com/hair/exosome-hair-treatment-malaysia/",
      "description": "Clinical trial data does not lie. Exosome therapy delivers 3x to 5x more growth factors than PRP to stimulate dormant hair follicles, promote hair growth, and regenerate the scalp. Nexus Clinic KL offers advanced exosome hair loss treatment in Malaysia for men and women in KL. Book your consultation today.",
      "serviceType": "Exosome Hair Loss Treatment in Malaysia for Advanced Hair Regeneration",

      "provider": {
        "@type": "MedicalClinic",
        "@id": "https://www.nexus-clinic.com#medicalclinic",
        "name": "Nexus Clinic",
        "url": "https://www.nexus-clinic.com"
      },
      "areaServed": {
        "@type": "Country",
        "name": "Malaysia"
      },
      "mainEntityOfPage": {
        "@type": "WebPage",
        "@id": "https://www.nexus-clinic.com/hair/exosome-hair-treatment-malaysia/"
      },
      "image": "https://www.nexus-clinic.com/images/logo.webp"
    },
    {
      "@type": "MedicalProcedure",
      "@id": "https://www.nexus-clinic.com/hair/exosome-hair-treatment-malaysia/#medicalprocedure",
      "name": "Exosome Hair Loss Treatment in Malaysia for Advanced Hair Regeneration",
      "url": "https://www.nexus-clinic.com/hair/exosome-hair-treatment-malaysia/",
      "description": "Clinical trial data does not lie. Exosome therapy delivers 3x to 5x more growth factors than PRP to stimulate dormant hair follicles, promote hair growth, and regenerate the scalp. Nexus Clinic KL offers advanced exosome hair loss treatment in Malaysia for men and women in KL. Book your consultation today.",
      "procedureType": "http://schema.org/NoninvasiveProcedure",
      "recognizingAuthority": {
        "@type": "Organization",
        "name": "Nexus Clinic"
      },
      "mainEntityOfPage": {
        "@type": "WebPage",
        "@id": "https://www.nexus-clinic.com/hair/exosome-hair-treatment-malaysia/"
      }
    }
  ]
}